dephell_venvs-0.1.18.dist-info/dependency_links.txt
dephell_venvs-0.1.18.dist-info/entry_points.txt
dephell_venvs-0.1.18.dist-info/METADATA
dephell_venvs-0.1.18.dist-info/top_level.txt
dephell_venvs-0.1.18.dist-info/WHEEL
dephell_venvs/_cached_property.py
dephell_venvs/_constants.py
dephell_venvs/_venv.py
dephell_venvs/_ensurepip.py
dephell_venvs/__init__.py
dephell_venvs/_venvs.py
dephell_venvs/_builder.py
dephell_venvs/ensurepip/__init__.py
dephell_venvs/ensurepip/__main__.py
dephell_venvs/ensurepip/_uninstall.py
dephell_venvs/ensurepip/_bundled/setuptools-40.6.2-py2.py3-none-any.whl
dephell_venvs/ensurepip/_bundled/pip-18.1-py2.py3-none-any.whl
dephell_venvs-0.1.18.dist-info/LICENSE
dephell_venvs-0.1.18.dist-info/RECORD