Metadata-Version: 2.1
Name: dephell-venvs
Version: 0.1.18
Summary: Manage virtual environments
Project-URL: Repository, https://github.com/dephell/dephell_venvs
Author: Gram
Author-email: master_fess@mail.ru
License: MIT
Requires-Python: >=3.5
Keywords: dephell,packaging,venv,pipenv,virtualenv
Classifier: Development Status :: 4 - Beta
Classifier: Environment :: Console
Classifier: Intended Audience :: Developers
Classifier: License :: OSI Approved :: MIT License
Classifier: Programming Language :: Python
Classifier: Topic :: Software Development :: Libraries :: Python Modules
Classifier: Topic :: System :: Installation/Setup
Classifier: Programming Language :: Python :: 3.5
Classifier: Programming Language :: Python :: 3.6
Classifier: Programming Language :: Python :: 3.7
Classifier: Programming Language :: Python :: 3.8
Classifier: Programming Language :: Python :: Implementation :: CPython
Classifier: Programming Language :: Python :: Implementation :: PyPy
Classifier: Operating System :: MacOS
Classifier: Operating System :: Microsoft :: Windows
Classifier: Operating System :: Unix
Requires-Dist: attrs
Requires-Dist: dephell-pythons
Requires-Dist: requests
